yxs_one2one.py
yxs_one2one-1.1.dist-info/METADATA
yxs_one2one-1.1.dist-info/WHEEL
yxs_one2one-1.1.dist-info/entry_points.txt
yxs_one2one-1.1.dist-info/top_level.txt
yxs_one2one-1.1.dist-info/RECORD
